quadbin/__init__.py
quadbin/_version.py
quadbin/main.py
quadbin/tilecover.py
quadbin/utils.py
quadbin-0.2.2.dist-info/LICENSE
quadbin-0.2.2.dist-info/METADATA
quadbin-0.2.2.dist-info/WHEEL
quadbin-0.2.2.dist-info/top_level.txt
quadbin-0.2.2.dist-info/RECORD
