Metadata-Version: 2.1
Name: quadbin
Version: 0.2.2
Summary: Hierarchical geospatial indexing system for square cells in Web Mercator projection
Home-page: https://github.com/cartodb/quadbin-py
Author: CARTO
Author-email: contact@carto.com
License: BSD 3-Clause
Keywords: quadbin,hierarchical,geospatial,index,visualization,maps,carto
Classifier: Development Status :: 3 - Alpha
Classifier: Intended Audience :: Developers
Classifier: Intended Audience :: Science/Research
Classifier: License :: OSI Approved :: BSD License
Classifier: Programming Language :: Python :: 2
Classifier: Programming Language :: Python :: 2.7
Classifier: Programming Language :: Python :: 3
Classifier: Programming Language :: Python :: 3.7
Classifier: Programming Language :: Python :: 3.8
Classifier: Programming Language :: Python :: 3.9
Classifier: Operating System :: MacOS :: MacOS X
Classifier: Operating System :: POSIX :: Linux
Classifier: Operating System :: Microsoft :: Windows
Classifier: Topic :: Scientific/Engineering :: GIS
Requires-Python: >=2.7
License-File: LICENSE
